edamam_api/Edamam.py
edamam_api/__init__.py
edamam_api-0.0.1.dist-info/METADATA
edamam_api-0.0.1.dist-info/RECORD
edamam_api-0.0.1.dist-info/WHEEL
edamam_api-0.0.1.dist-info/top_level.txt
