Metadata-Version: 2.1
Name: edamam-api
Version: 0.0.1
Summary: Python library to interface with the edamam API
Home-page: https://github.com/lirwin3007/edamam-python
Author: Louis Irwin
Author-email: coding@louisirwin.co.uk
License: UNKNOWN
Platform: UNKNOWN
Classifier: Programming Language :: Python :: 3
Classifier: License :: OSI Approved :: GNU Affero General Public License v3
Classifier: Operating System :: OS Independent
